llamonitor_async-0.2.0.dist-info/licenses/LICENSE
llmops_monitoring/__init__.py
llmops_monitoring/aggregation/__init__.py
llmops_monitoring/aggregation/service.py
llmops_monitoring/api/__init__.py
llmops_monitoring/api/models.py
llmops_monitoring/api/server.py
llmops_monitoring/data/pricing.json
llmops_monitoring/examples/01_simple_example.py
llmops_monitoring/examples/02_agentic_workflow.py
llmops_monitoring/examples/03_custom_collector.py
llmops_monitoring/examples/04_mysql_backend.py
llmops_monitoring/examples/05_cost_calculation.py
llmops_monitoring/examples/06_prometheus_exporter.py
llmops_monitoring/examples/07_aggregation_api.py
llmops_monitoring/examples/08_websocket_streaming.py
llmops_monitoring/exporters/__init__.py
llmops_monitoring/exporters/base.py
llmops_monitoring/exporters/prometheus.py
llmops_monitoring/instrumentation/__init__.py
llmops_monitoring/instrumentation/base.py
llmops_monitoring/instrumentation/context.py
llmops_monitoring/instrumentation/decorators.py
llmops_monitoring/instrumentation/collectors/__init__.py
llmops_monitoring/instrumentation/collectors/cost.py
llmops_monitoring/instrumentation/collectors/image.py
llmops_monitoring/instrumentation/collectors/text.py
llmops_monitoring/schema/__init__.py
llmops_monitoring/schema/config.py
llmops_monitoring/schema/events.py
llmops_monitoring/streaming/__init__.py
llmops_monitoring/streaming/broadcaster.py
llmops_monitoring/streaming/connection_manager.py
llmops_monitoring/transport/__init__.py
llmops_monitoring/transport/writer.py
llmops_monitoring/transport/backends/__init__.py
llmops_monitoring/transport/backends/base.py
llmops_monitoring/transport/backends/mysql.py
llmops_monitoring/transport/backends/mysql_query.py
llmops_monitoring/transport/backends/parquet.py
llmops_monitoring/transport/backends/parquet_query.py
llmops_monitoring/transport/backends/postgres.py
llmops_monitoring/transport/backends/postgres_query.py
llmops_monitoring/transport/backends/query_base.py
llmops_monitoring/utils/__init__.py
llamonitor_async-0.2.0.dist-info/METADATA
llamonitor_async-0.2.0.dist-info/WHEEL
llamonitor_async-0.2.0.dist-info/top_level.txt
llamonitor_async-0.2.0.dist-info/RECORD
