Metadata-Version: 2.4
Name: llamonitor-async
Version: 0.2.0
Summary: Lightweight async monitoring for LLM applications - capacity-based tracking with pluggable storage
Author: LLMOps Monitoring Contributors
License: Apache-2.0
Project-URL: Homepage, https://github.com/guybass/LLMOps_monitoring_async-
Project-URL: Documentation, https://github.com/guybass/LLMOps_monitoring_async-/blob/main/README.md
Project-URL: Repository, https://github.com/guybass/LLMOps_monitoring_async-
Project-URL: Issues, https://github.com/guybass/LLMOps_monitoring_async-/issues
Keywords: llm,monitoring,observability,async,telemetry
Classifier: Development Status :: 3 - Alpha
Classifier: Intended Audience :: Developers
Classifier: License :: OSI Approved :: Apache Software License
Classifier: Programming Language :: Python :: 3.10
Classifier: Programming Language :: Python :: 3.11
Classifier: Programming Language :: Python :: 3.12
Classifier: Topic :: Software Development :: Libraries :: Python Modules
Classifier: Topic :: System :: Monitoring
Requires-Python: >=3.10
License-File: LICENSE
Requires-Dist: pydantic>=2.0.0
Requires-Dist: aiofiles>=23.0.0
Requires-Dist: python-dotenv>=1.0.0
Provides-Extra: parquet
Requires-Dist: pandas>=2.0.0; extra == "parquet"
Requires-Dist: pyarrow>=12.0.0; extra == "parquet"
Provides-Extra: postgres
Requires-Dist: asyncpg>=0.29.0; extra == "postgres"
Requires-Dist: sqlalchemy>=2.0.0; extra == "postgres"
Provides-Extra: mysql
Requires-Dist: aiomysql>=0.2.0; extra == "mysql"
Requires-Dist: sqlalchemy>=2.0.0; extra == "mysql"
Provides-Extra: prometheus
Requires-Dist: prometheus-client>=0.19.0; extra == "prometheus"
Provides-Extra: api
Requires-Dist: fastapi>=0.104.0; extra == "api"
Requires-Dist: uvicorn[standard]>=0.24.0; extra == "api"
Provides-Extra: all
Requires-Dist: llamonitor-async[api,mysql,parquet,postgres,prometheus]; extra == "all"
Provides-Extra: dev
Requires-Dist: pytest>=7.0.0; extra == "dev"
Requires-Dist: pytest-asyncio>=0.21.0; extra == "dev"
Requires-Dist: pytest-cov>=4.0.0; extra == "dev"
Requires-Dist: black>=23.0.0; extra == "dev"
Requires-Dist: ruff>=0.1.0; extra == "dev"
Requires-Dist: mypy>=1.5.0; extra == "dev"
Requires-Dist: mkdocs>=1.5.0; extra == "dev"
Requires-Dist: mkdocs-material>=9.0.0; extra == "dev"
Dynamic: license-file
